[
    {
        "ids": [
            0,
            4,
            8
        ],
        "doc_id": "votes_fgjj0009_page1",
        "pii_type": "Person Name",
        "value": "Plaia, Gina",
        "annotators": [
            0,
            1,
            2
        ],
        "bbox": [
            453,
            200,
            597,
            228
        ],
        "source_file": "votes_fgjj0009_page1.csv",
        "votes": [
            1,
            0,
            1,
            1,
            1,
            1
        ],
        "probability": 0.9999997859950661
    },
    {
        "ids": [
            1,
            5,
            9
        ],
        "doc_id": "votes_fgjj0009_page1",
        "pii_type": "Person Name",
        "value": "Elfar, Deb",
        "annotators": [
            0,
            1,
            2
        ],
        "bbox": [
            418,
            263,
            549,
            292
        ],
        "source_file": "votes_fgjj0009_page1.csv",
        "votes": [
            1,
            0,
            1,
            1,
            1,
            1
        ],
        "probability": 0.9999997859950661
    },
    {
        "ids": [
            2,
            6,
            10
        ],
        "doc_id": "votes_fgjj0009_page1",
        "pii_type": "Person Name",
        "value": "Rush, Sonya",
        "annotators": [
            0,
            1,
            2
        ],
        "bbox": [
            419,
            294,
            586,
            326
        ],
        "source_file": "votes_fgjj0009_page1.csv",
        "votes": [
            1,
            0,
            1,
            1,
            1,
            1
        ],
        "probability": 0.9999997859950661
    },
    {
        "ids": [
            3,
            7,
            11
        ],
        "doc_id": "votes_fgjj0009_page1",
        "pii_type": "Date",
        "value": "Thu, Mar 24, 1994 5:07 PM",
        "annotators": [
            0,
            1,
            2
        ],
        "bbox": [
            643,
            199,
            1005,
            229
        ],
        "source_file": "votes_fgjj0009_page1.csv",
        "votes": [
            1,
            1,
            1,
            1,
            1,
            1
        ],
        "probability": 0.999999713175462
    }
]