[
    {
        "ids": [
            0,
            5,
            10
        ],
        "doc_id": "votes_fgcg0076_page1",
        "pii_type": "Person Name",
        "value": "DALE HILL",
        "annotators": [
            0,
            1,
            2
        ],
        "bbox": [
            365,
            504,
            526,
            531
        ],
        "source_file": "votes_fgcg0076_page1.csv",
        "votes": [
            1,
            0,
            1,
            1,
            1,
            1
        ],
        "probability": 0.9999997859950661
    },
    {
        "ids": [
            1,
            6,
            11
        ],
        "doc_id": "votes_fgcg0076_page1",
        "pii_type": "Person Name",
        "value": "Cindy Arterbery",
        "annotators": [
            0,
            1,
            2
        ],
        "bbox": [
            364,
            578,
            569,
            610
        ],
        "source_file": "votes_fgcg0076_page1.csv",
        "votes": [
            1,
            0,
            1,
            1,
            1,
            1
        ],
        "probability": 0.9999997859950661
    },
    {
        "ids": [
            2,
            7
        ],
        "doc_id": "votes_fgcg0076_page1",
        "pii_type": "Location",
        "value": "RICHMOND, VIRGINIA",
        "annotators": [
            0,
            1
        ],
        "bbox": [
            776,
            391,
            954,
            410
        ],
        "source_file": "votes_fgcg0076_page1.csv",
        "votes": [
            1,
            1,
            1,
            1,
            1,
            1
        ],
        "probability": 0.9999997426401738
    },
    {
        "ids": [
            3,
            8,
            12
        ],
        "doc_id": "votes_fgcg0076_page1",
        "pii_type": "Organization Name",
        "value": "PHILIP MORRIS U.S.A.",
        "annotators": [
            0,
            1,
            2
        ],
        "bbox": [
            646,
            223,
            1086,
            260
        ],
        "source_file": "votes_fgcg0076_page1.csv",
        "votes": [
            1,
            0,
            1,
            1,
            1,
            1
        ],
        "probability": 0.9999159454539699
    },
    {
        "ids": [
            4,
            9,
            13
        ],
        "doc_id": "votes_fgcg0076_page1",
        "pii_type": "Date",
        "value": "June 26, 1995",
        "annotators": [
            0,
            1,
            2
        ],
        "bbox": [
            1143,
            510,
            1316,
            540
        ],
        "source_file": "votes_fgcg0076_page1.csv",
        "votes": [
            1,
            1,
            1,
            1,
            1,
            1
        ],
        "probability": 0.999999713175462
    }
]