[
    {
        "ids": [
            0,
            18,
            37
        ],
        "doc_id": "votes_fhyg0235_page1",
        "pii_type": "Person Name",
        "value": "Missy Henry",
        "annotators": [
            0,
            1,
            2
        ],
        "bbox": [
            0.3400867283344269,
            0.23892562091350555,
            0.4420068599283695,
            0.2536446126177907
        ],
        "source_file": "votes_fhyg0235_page1.csv"
    },
    {
        "ids": [
            1,
            19,
            38
        ],
        "doc_id": "votes_fhyg0235_page1",
        "pii_type": "Person Name",
        "value": "Diana Walker",
        "annotators": [
            0,
            1,
            2
        ],
        "bbox": [
            0.2767000198364258,
            0.294691801071167,
            0.39689477533102036,
            0.3065320663154125
        ],
        "source_file": "votes_fhyg0235_page1.csv"
    },
    {
        "ids": [
            2,
            20,
            39
        ],
        "doc_id": "votes_fhyg0235_page1",
        "pii_type": "Person Name",
        "value": "Diana",
        "annotators": [
            0,
            1,
            2
        ],
        "bbox": [
            0.14484158158302307,
            0.46310338377952576,
            0.19173425808548927,
            0.4748649401590228
        ],
        "source_file": "votes_fhyg0235_page1.csv"
    },
    {
        "ids": [
            3,
            21,
            40
        ],
        "doc_id": "votes_fhyg0235_page1",
        "pii_type": "Person Name",
        "value": "Diana",
        "annotators": [
            0,
            1,
            2
        ],
        "bbox": [
            0.7549303770065308,
            0.497946172952652,
            0.8026806637644768,
            0.509830572642386
        ],
        "source_file": "votes_fhyg0235_page1.csv"
    },
    {
        "ids": [
            4,
            22,
            41
        ],
        "doc_id": "votes_fhyg0235_page1",
        "pii_type": "Person Name",
        "value": "Diana",
        "annotators": [
            0,
            1,
            2
        ],
        "bbox": [
            0.1443483531475067,
            0.5663767457008362,
            0.1913546361029148,
            0.5783425662666559
        ],
        "source_file": "votes_fhyg0235_page1.csv"
    },
    {
        "ids": [
            5,
            23
        ],
        "doc_id": "votes_fhyg0235_page1",
        "pii_type": "Person Name",
        "value": "Diana",
        "annotators": [
            0,
            1
        ],
        "bbox": [
            0.553175151348114,
            0.8751537799835205,
            0.6008491963148117,
            0.8872218951582909
        ],
        "source_file": "votes_fhyg0235_page1.csv"
    },
    {
        "ids": [
            6,
            9,
            24,
            27,
            43,
            48
        ],
        "doc_id": "votes_fhyg0235_page1",
        "pii_type": [
            "Location",
            "Email Address"
        ],
        "value": "Diana.Walker@fda.hhs.gov",
        "annotators": [
            0,
            1,
            2
        ],
        "bbox": [
            0.21240772306919098,
            0.37202173471450806,
            0.4460234194993973,
            0.3870200663805008
        ],
        "source_file": "votes_fhyg0235_page1.csv"
    },
    {
        "ids": [
            7,
            8,
            25,
            26,
            44,
            47
        ],
        "doc_id": "votes_fhyg0235_page1",
        "pii_type": [
            "Phone Number",
            "Location"
        ],
        "value": "301-796-4029",
        "annotators": [
            0,
            1,
            2
        ],
        "bbox": [
            0.28321561217308044,
            0.34617602825164795,
            0.39629240334033966,
            0.35822859965264797
        ],
        "source_file": "votes_fhyg0235_page1.csv"
    },
    {
        "ids": [
            10,
            29,
            50
        ],
        "doc_id": "votes_fhyg0235_page1",
        "pii_type": "Location",
        "value": "https://www.industrydocuments.ucsf.edu/docs/fhyg0235 MNKOI 0000391265",
        "annotators": [
            0,
            1,
            2
        ],
        "bbox": [
            0.285759299993515,
            0.9812459945678711,
            0.9675274938344955,
            0.9976854473352432
        ],
        "source_file": "votes_fhyg0235_page1.csv"
    },
    {
        "ids": [
            11,
            30,
            45,
            51
        ],
        "doc_id": "votes_fhyg0235_page1",
        "pii_type": [
            "Location",
            "Organization Name"
        ],
        "value": "Mallinckrodt Inc.",
        "annotators": [
            0,
            1,
            2
        ],
        "bbox": [
            0.1465136557817459,
            0.11685823649168015,
            0.2991742193698883,
            0.12940563075244427
        ],
        "source_file": "votes_fhyg0235_page1.csv"
    },
    {
        "ids": [
            12,
            31
        ],
        "doc_id": "votes_fhyg0235_page1",
        "pii_type": "Organization Name",
        "value": "Mallinckrodt",
        "annotators": [
            0,
            1
        ],
        "bbox": [
            0.14466693997383118,
            0.23878373205661774,
            0.2563561424612999,
            0.2509419349953532
        ],
        "source_file": "votes_fhyg0235_page1.csv"
    },
    {
        "ids": [
            13,
            32,
            52
        ],
        "doc_id": "votes_fhyg0235_page1",
        "pii_type": "Date",
        "value": "03.22.10",
        "annotators": [
            0,
            1,
            2
        ],
        "bbox": [
            0.20318734645843506,
            0.16196638345718384,
            0.27285484224557877,
            0.1739147985354066
        ],
        "source_file": "votes_fhyg0235_page1.csv"
    },
    {
        "ids": [
            14,
            33,
            53
        ],
        "doc_id": "votes_fhyg0235_page1",
        "pii_type": "Date",
        "value": "March 12, 2010",
        "annotators": [
            0,
            1,
            2
        ],
        "bbox": [
            0.34951308369636536,
            0.7210312485694885,
            0.48162926360964775,
            0.7354418411850929
        ],
        "source_file": "votes_fhyg0235_page1.csv"
    },
    {
        "ids": [
            15,
            34,
            54
        ],
        "doc_id": "votes_fhyg0235_page1",
        "pii_type": "Date",
        "value": "1/15/2008",
        "annotators": [
            0,
            1,
            2
        ],
        "bbox": [
            0.793234646320343,
            0.9259750843048096,
            0.8518650382757187,
            0.934979478828609
        ],
        "source_file": "votes_fhyg0235_page1.csv"
    },
    {
        "ids": [
            16,
            55
        ],
        "doc_id": "votes_fhyg0235_page1",
        "pii_type": "Contract Number",
        "value": "NDA 021217",
        "annotators": [
            0,
            2
        ],
        "bbox": [
            0.2885901629924774,
            0.18775182962417603,
            0.39666159078478813,
            0.19928839802742004
        ],
        "source_file": "votes_fhyg0235_page1.csv"
    },
    {
        "ids": [
            17,
            35,
            56
        ],
        "doc_id": "votes_fhyg0235_page1",
        "pii_type": "Contract Number",
        "value": "S-001",
        "annotators": [
            0,
            1,
            2
        ],
        "bbox": [
            0.7536638975143433,
            0.5496149659156799,
            0.8051412478089333,
            0.563768164254725
        ],
        "source_file": "votes_fhyg0235_page1.csv"
    },
    {
        "ids": [
            28,
            36,
            49
        ],
        "doc_id": "votes_fhyg0235_page1",
        "pii_type": [
            "Contract Number",
            "Location"
        ],
        "value": "S:\\Contact Report Template.doc",
        "annotators": [
            1,
            2
        ],
        "bbox": [
            0.14487884938716888,
            0.9259623289108276,
            0.33300498127937317,
            0.9378033736720681
        ],
        "source_file": "votes_fhyg0235_page1.csv"
    },
    {
        "ids": [
            42
        ],
        "doc_id": "votes_fhyg0235_page1",
        "pii_type": "Person Name",
        "value": "Missy",
        "annotators": [
            2
        ],
        "bbox": [
            0.1446554809808731,
            0.8409281373023987,
            0.19224267452955246,
            0.8553432580083609
        ],
        "source_file": "votes_fhyg0235_page1.csv"
    },
    {
        "ids": [
            46
        ],
        "doc_id": "votes_fhyg0235_page1",
        "pii_type": "Location",
        "value": "FDA/CDER/DAAP",
        "annotators": [
            2
        ],
        "bbox": [
            0.30534958839416504,
            0.32054996490478516,
            0.46862873435020447,
            0.3326878026127815
        ],
        "source_file": "votes_fhyg0235_page1.csv"
    }
]